shared_constructs/__init__.py
shared_constructs/aws/__init__.py
shared_constructs/aws/s3.py
shared_constructs/config.py
shared_constructs-1.0.8.dist-info/LICENSE
shared_constructs-1.0.8.dist-info/METADATA
shared_constructs-1.0.8.dist-info/WHEEL
shared_constructs-1.0.8.dist-info/RECORD
